KPAPI/__init__.py
KPAPI/kpapi.py
KPAPI-1.1.0.dist-info/LICENSE
KPAPI-1.1.0.dist-info/METADATA
KPAPI-1.1.0.dist-info/WHEEL
KPAPI-1.1.0.dist-info/top_level.txt
KPAPI-1.1.0.dist-info/RECORD
