Metadata-Version: 2.1
Name: KPAPI
Version: 1.1.0
Summary: Facebook API for chat bot app
Author: Khang Phan
Author-email: duykhang4341@gmail.com
Classifier: License :: OSI Approved :: MIT License
Classifier: Programming Language :: Python :: 3
Classifier: Operating System :: OS Independent
License-File: LICENSE
